TrER/CVaR_calculate.py
TrER/IF_calculate.py
TrER/__init__.py
TrER/gen_cvar.py
TrER/main.py
TrER/models.py
TrER/plots.py
TrER/utils.py
TrER/utils_plots.py
TrER-0.2.0.dist-info/LICENSE
TrER-0.2.0.dist-info/METADATA
TrER-0.2.0.dist-info/WHEEL
TrER-0.2.0.dist-info/top_level.txt
TrER-0.2.0.dist-info/RECORD
