Metadata-Version: 2.1
Name: TrER
Version: 0.2.0
Summary: implementation of the Treatment Effect Risk: Bounds and Inference package, based on the replication by Kallus (2024).
Home-page: https://github.com/d2cml-ai/TreatmentEffectRisk
Author: Jhon Flores Rojas
Author-email: fr.jhonk@gmail.com
Classifier: Programming Language :: Python :: 3
Classifier: License :: OSI Approved :: MIT License
Classifier: Operating System :: OS Independent
Requires-Python: >=3.6
License-File: LICENSE
Requires-Dist: pandas
Requires-Dist: numpy
Requires-Dist: ipykernel
Requires-Dist: patsy
Requires-Dist: statsmodels
Requires-Dist: scikit-learn
Requires-Dist: matplotlib
